<?xml version="1.0" encoding="utf-8"?>
<openerp>
    <data>

        <!-- Supplier Tree View -->

        <record id="view_partner_supplier_tree_portal_usermgt" model="ir.ui.view">
            <field name="name">res.partner.tree</field>
            <field name="model">res.partner</field>
            <field name="inherit_id" ref="base.view_partner_tree"/>
            <field name="arch" type="xml">
                    <field name="name" position="after">
                        <field name="user_ids"/>
                        <field name="reuse" string="Hergebruik"/>
                        <field name="var_ok" string="VAR OK"/>
                        <field name="genexp_portal" string="AK Portal"/>
                    </field>
            </field>
        </record>

        <!-- Supplier Form View -->

        <record id="view_nsm_res_partner_form_ext" model="ir.ui.view">
            <field name="name">res.partner.form_ext</field>
            <field name="model">res.partner</field>
            <field name="type">form</field>
            <field name="inherit_id" ref="base.view_partner_form"/>
            <field name="arch" type="xml">
                <field name="var_ok" position="after">
                    <field name="genexp_portal" string="Algemene Kosten Portal"/>
                </field>
            </field>
        </record>

    </data>
</openerp>
